README.md
setup.py
drf_api_key/__init__.py
drf_api_key/admin.py
drf_api_key/managers.py
drf_api_key/models.py
drf_api_key/permissions.py
drf_api_key/throttling.py
drf_api_key/utils.py
drf_api_key/migrations/0001_initial.py
drf_api_key/migrations/__init__.py
drf_api_key_auth.egg-info/PKG-INFO
drf_api_key_auth.egg-info/SOURCES.txt
drf_api_key_auth.egg-info/dependency_links.txt
drf_api_key_auth.egg-info/not-zip-safe
drf_api_key_auth.egg-info/top_level.txt