Metadata-Version: 2.1
Name: drf-api-key-auth
Version: 0.3.0
Summary: Django rest library for creating, managing and securing API keys
Home-page: https://github.com/temi9568/drf_api_key_auth
Author: Temi Olatunji
Author-email: temiolatunji95@gmail.com
License: MIT
Platform: UNKNOWN
Classifier: Development Status :: 3 - Alpha
Classifier: Intended Audience :: Developers
Classifier: License :: OSI Approved :: MIT License
Classifier: Programming Language :: Python :: 3
Classifier: Programming Language :: Python :: 3.6
Classifier: Programming Language :: Python :: 3.7
Classifier: Programming Language :: Python :: 3.8
Classifier: Programming Language :: Python :: 3.9
Requires-Python: >=3.6
